Metadata-Version: 1.0
Name: bright-vc
Version: 1.1.1
Summary: Bright Interactive Version Control
Home-page: http://github.com/brightinteractive/bright-vc/
Author: Bright Interactive
Author-email: francis@bright-interactive.co.uk
License: BSD
Platform: UNKNOWN
